vendor_colors/__init__.py
vendor_colors/ant_design_colors.py
vendor_colors/material_design_colors.py
vendor_colors/tailwindcss_colors.py
vendor_color_swatches_py-0.0.0.dist-info/LICENSE.txt
vendor_color_swatches_py-0.0.0.dist-info/METADATA
vendor_color_swatches_py-0.0.0.dist-info/WHEEL
vendor_color_swatches_py-0.0.0.dist-info/top_level.txt
vendor_color_swatches_py-0.0.0.dist-info/RECORD
