Metadata-Version: 2.1
Name: vendor-color-swatches-py
Version: 0.0.0
Summary: Use color swatches/palettes from popular providers (Material Design, Ant, TailwindCSS)
Home-page: https://github.com/aufarijaal/vendor_color_swaches_py
Author: Muhammad Aufa Rijal
Author-email: rijalaufa0@gmail.com
License: MIT
Download-URL: https://pypi.org/project/vendor_color_swaches_py/
Keywords: Color,MaterialDesign,Ant,AntDesign,MD,TailwindCSS,Tailwind,ColorPalettes,ColorSwatches
Platform: UNKNOWN
